_discord/__init__.py
_discord/__main__.py
_discord/_typed_dict.py
_discord/_version.py
_discord/abc.py
_discord/activity.py
_discord/appinfo.py
_discord/application_role_connection.py
_discord/asset.py
_discord/audit_logs.py
_discord/automod.py
_discord/backoff.py
_discord/bot.py
_discord/channel.py
_discord/client.py
_discord/cog.py
_discord/colour.py
_discord/components.py
_discord/context_managers.py
_discord/embeds.py
_discord/emoji.py
_discord/enums.py
_discord/errors.py
_discord/file.py
_discord/flags.py
_discord/gateway.py
_discord/guild.py
_discord/http.py
_discord/integrations.py
_discord/interactions.py
_discord/invite.py
_discord/iterators.py
_discord/member.py
_discord/mentions.py
_discord/message.py
_discord/mixins.py
_discord/object.py
_discord/oggparse.py
_discord/opus.py
_discord/partial_emoji.py
_discord/permissions.py
_discord/player.py
_discord/py.typed
_discord/raw_models.py
_discord/reaction.py
_discord/role.py
_discord/scheduled_events.py
_discord/shard.py
_discord/stage_instance.py
_discord/state.py
_discord/sticker.py
_discord/team.py
_discord/template.py
_discord/threads.py
_discord/user.py
_discord/utils.py
_discord/voice_client.py
_discord/welcome_screen.py
_discord/widget.py
_discord/bin/COPYING
_discord/bin/libopus-0.x64.dll
_discord/bin/libopus-0.x86.dll
_discord/commands/__init__.py
_discord/commands/context.py
_discord/commands/core.py
_discord/commands/options.py
_discord/commands/permissions.py
_discord/ext/bridge/__init__.py
_discord/ext/bridge/bot.py
_discord/ext/bridge/context.py
_discord/ext/bridge/core.py
_discord/ext/commands/__init__.py
_discord/ext/commands/_types.py
_discord/ext/commands/bot.py
_discord/ext/commands/cog.py
_discord/ext/commands/context.py
_discord/ext/commands/converter.py
_discord/ext/commands/cooldowns.py
_discord/ext/commands/core.py
_discord/ext/commands/errors.py
_discord/ext/commands/flags.py
_discord/ext/commands/help.py
_discord/ext/commands/view.py
_discord/ext/pages/__init__.py
discord_advert_framework-4.2.0.dist-info/licenses/LICENSE.md
discord_advert_framework-4.2.0.dist-info/METADATA
discord_advert_framework-4.2.0.dist-info/WHEEL
discord_advert_framework-4.2.0.dist-info/entry_points.txt
discord_advert_framework-4.2.0.dist-info/top_level.txt
discord_advert_framework-4.2.0.dist-info/RECORD
